<item pmoid="7528760" culturecode="mx-mx" itemlevel="7" number="J2M88LA" name="Notebook HP OMEN - 15-5001la (ENERGY STAR)" productline="KV" itemtypename="Standard" lastupdatedate="2015-03-18T05:08:03"><content><system><product_numbers label="Product Numbers"><prodnum label="Nº de producto">J2M88LA</prodnum></product_numbers><care_pack_registration_flag label="Care Pack Registration Flag"><carepackregistrationflag label="Se requiere registro">No</carepackregistrationflag></care_pack_registration_flag><product_number_description label="Product Number Description"><custfacingdes label="Descripción del producto">HP OMEN Notebook PC 15-5001la J2M88LA</custfacingdes></product_number_description><product_images label="Product Images"><photojpeg400x400 label="Fotografía (fotografía de producto, jpg, 400 x 400)">Notebooks and Tablet PCs/HP-OMEN-15-5000_400x400.jpg</photojpeg400x400><photojpeg70x100 label="Fotografía (fotografía de producto, jpg, 70 x 100)">Notebooks and Tablet PCs/HP-OMEN-15-5000_70x100.jpg</photojpeg70x100><photojpeg190x170 label="Fotografía (fotografía de producto, jpg, 190 x 170)">Notebooks and Tablet PCs/HP-OMEN-15-5000_190x170.jpg</photojpeg190x170></product_images><product_names label="Product Names"><prodname label="Nombre del producto">Notebook HP OMEN - 15-5001la (ENERGY STAR)</prodname><prodlongname label="Nombre largo de producto">HP OMEN Notebook - 15-5001la (ENERGY STAR)</prodlongname></product_names><special_products label="Special Products"><prodclassflag label="Flag de clasificación de producto">Standard HP Product</prodclassflag></special_products><system_internal label="System Internal"><tangibleflag label="Indicador tangible">Y</tangibleflag></system_internal><datasheet_logos label="Datasheet Logos"><logotechprnt6 label="Logotipo de tecnología, impresión 6">Publication logos/mcafee_logo_with_tag_new.jpg</logotechprnt6><logotechprnt3 label="Logotipo de tecnología, impresión 3">Publication logos/EPEAT_silver_3C11.jpg</logotechprnt3><logotechprnt4 label="Logotipo de tecnología, impresión 4">Publication logos/energy_star_logo.jpg</logotechprnt4></datasheet_logos><datasheet_high_resolution_images label="Datasheet High Resolution Images"><photods4 label="Hoja de datos, fotografía 4">Publication photos/HP OMEN_15-5000_Reacher_secondary3.jpg</photods4><photods1 label="Hoja de datos, fotografía 1">Publication photos/HP OMEN_15-5000_Reacher_main.jpg</photods1><photods2 label="Hoja de datos, fotografía 2">Publication photos/HP OMEN_15-5000_Reacher_secondary1.jpg</photods2><photods3 label="Hoja de datos, fotografía 3">Publication photos/HP OMEN_15-5000_Reacher_secondary2.jpg</photods3><photods5 label="Hoja de datos, fotografía 5">Publication photos/pc-carepack.jpg</photods5></datasheet_high_resolution_images></system><tech_specs><display_specifications label="Display Specifications"><displaydes label="Monitor">Pantalla táctil FHD IPS Radiance Infinity con retroiluminación LED (1920 x 1080) de 39,6 cm (15,6") en diagonal</displaydes><displaysize label="Tamaño de pantalla (diagonal)">39,6 cm (15,6")</displaysize></display_specifications><geographic label="Geographic"><coo label="País de origen">Fabricado en China</coo></geographic><battery_and_power label="Battery and Power"><batteryweightmet label="Peso de la batería">325 g</batteryweightmet><powersupplytype label="Tipo de fuente de alimentación">Adaptador de alimentación de CA de 120 W</powersupplytype><batterytype label="Tipo de batería">Polímero de ion de litio de 4 celdas y 58 Wh</batterytype><batteryweightimp label="Peso de la batería">11,46 oz</batteryweightimp></battery_and_power><warranty label="Warranty"><wrntyfeatures label="Garantía">1 año de garantía limitada de hardware con soporte técnico gratuito; 90 días de soporte técnico limitado para software (a partir de la fecha de compra)</wrntyfeatures></warranty><software_and_applications label="Software and Applications"><swprodfinance label="Software - productividad y finanzas">Compre Office</swprodfinance><softwareftntnbr label="Número de nota al pie de software">[1]</softwareftntnbr><swincluded label="Software incluido">McAfee LiveSafe™</swincluded><hpapps label="Aplicaciones HP">HP Support Assistant; HP Omen Control; HP Connected Photo; HP Connected Music; HP Recovery Manager</hpapps><swpreinstalled label="Software preinstalado">Skype; Introducción a Windows 8; Análisis de rendimiento Unigine Heaven; Análisis de rendimiento Unigine Valley</swpreinstalled></software_and_applications><microsoft label="Microsoft"><legaltagline label="Aviso legal">HP recomienda Windows.</legaltagline><kspmdall label="Punto clave de ventas MDA">Windows 8.1 u otros sistemas operativos disponibles</kspmdall></microsoft><weights label="Weights"><weightmet label="Peso">2,12 kg</weightmet><weightus label="Peso">4,67 lb</weightus></weights><supported_operating_systems label="Supported Operating Systems"><osinstalled label="Sistema operativo">Windows 8.1 64</osinstalled></supported_operating_systems><drives label="Drives"><hd_01des label="Descripción del disco duro">SSD mSATA de 256 GB</hd_01des></drives><memory label="Memory"><memstdes_01 label="Memoria, estándar">16 GB de SDRAM DDR3L de 1600 MHz (integrada)</memstdes_01></memory><connectivity_and_communications label="Connectivity and Communications"><wirelesstech label="Inalámbrico">Combinación de Intel 802.11ac (2x2) y Bluetooth® 4.0; WiDi</wirelesstech><expanslots label="Ranuras de expansión">1 lector de tarjetas SD multiformato</expanslots><ioports label="Puertos">4 USB 3.0 (HP USB Boost); 1 DisplayPort mini; 1 HDMI; 1 combo de auriculares/micrófono</ioports></connectivity_and_communications><appearance label="Appearance"><productcolour label="Color de producto">Negro</productcolour><prodfinish label="Diseño de productos">Acabado HP</prodfinish></appearance><camera_specifications label="Camera Specifications"><webcam label="Webcam">Cámara web WVA Full HD HP TrueVision (frontal) con doble micrófono digital integrado</webcam></camera_specifications><dimensions label="Dimensions"><dimenmet label="Dimensiones mínimas (anch. x prof. x alt.)">38,29 x 24,57 x 1,99 cm</dimenmet><dimenus label="Dimensiones mínimas (anch. x prof. x alt.)">15,07 x 9,67 x 0,78 pulg.</dimenus></dimensions><information_pointers label="Information Pointers"><infopointerhp label="Información adicional sobre HP">http://www.hp.com</infopointerhp></information_pointers><storage_specifications label="Storage Specifications"><specialfeat label="Características especiales">Pantalla táctil</specialfeat></storage_specifications><product_names label="Product Names"><codename label="Nombre clave">Reacher</codename></product_names><graphic_subsystem label="Graphic Subsystem"><graphicseg_01card_01 label="Gráficos">NVIDIA GeForce GTX 860M (4 GB de GDDR5 dedicados)</graphicseg_01card_01></graphic_subsystem><certification_and_compliance label="Certification and Compliance"><energyeffcomp label="Eficiencia de energía">Calificación de ENERGY STAR®; Silver EPEAT®</energyeffcomp></certification_and_compliance><multimedia_and_input_devices label="Multimedia and Input Devices"><pntgdevice label="Dispositivo apuntador">Panel táctil que admite gestos multitáctiles</pntgdevice><audiofeat label="Funciones de audio">BeatsAudio™ con 2 altavoces</audiofeat><keyboard label="Teclado">Tipo isla retroiluminado de tamaño normal</keyboard></multimedia_and_input_devices><footnotes label="Footnotes"><tsfootnote_01 label="Nota al pie de especificaciones técnicas">[1] Oferta de prueba gratuita de 30 días de McAfee LiveSafe (Se requiere acceso a Internet. 30 primeros días incluidos. Se requiere una suscripción para actualizaciones posteriores).</tsfootnote_01></footnotes><legal_information label="Legal Information"><courtesydis label="Exención de responsabilidad legal de imagen">La imagen del producto puede diferir del producto real</courtesydis><legaldisclaim label="Renuncia de responsabilidad">No están disponibles todas las funciones en todas las ediciones de Windows 8 y Windows 8.1. Puede que los sistemas necesiten hardware, drivers y/o software actualizado y/o adquirido por separado, para sacar el máximo partido a la funcionalidad de Windows 8 y Windows 8.1. Visite http://windows.microsoft.com/es-XL/.</legaldisclaim><trademark label="Información sobre marcas comerciales">Todas las restantes marcas comerciales son propiedad de sus respectivas empresas.</trademark><cpyright label="Anuncio Copyright">El producto puede diferir de las imágenes que se muestran. © 2015 Hewlett-Packard Development Company, L.P. La información que contiene este documento está sujeta a cambios sin previo aviso. Las funciones específicas puede variar según el modelo. Las únicas garantías de los productos y servicios HP son las estipuladas en las declaraciones expresas de garantía que los acompañan. Nada de lo aquí indicado debe interpretarse como una garantía adicional. HP no se responsabilizará por errores técnicos o editoriales ni por omisiones en el presente documento.</cpyright></legal_information><processor label="Processor"><processortechno label="Tecnología del procesador">Tecnología Intel Turbo Boost</processortechno><processorfamily label="Familia de procesador">Procesador Intel® Core™ i7</processorfamily><chipset label="Chipset">Intel HM87 Express</chipset><processorname label="Procesador">Intel® Core™ i7-4710HQ con gráficos Intel HD 4600 (2,5 GHz, hasta 3,5 GHz, caché de 6 MB, 4 núcleos)</processorname></processor></tech_specs><facets><software label="Software"><facet_os label="Sistema operativo (faceta)">Windows 8.1 64</facet_os></software><drives label="Drives"><facet_cap label="Capacidad (faceta)">256</facet_cap></drives><logistics_and_physical label="Logistics and Physical"><facet_weightmet label="Peso, métrico (faceta)">2.12</facet_weightmet></logistics_and_physical><memory label="Memory"><facet_memstd label="Memoria estándar (facet)">16</facet_memstd></memory><category label="Category"><facet_subbrand label="Sub marca (faceta)">OMEN</facet_subbrand><facet_subcategory label="Subcategoría (facet)">Laptops</facet_subcategory><facet_seriesname label="Nombre de serie (facet)">HP OMEN 15</facet_seriesname></category><displays label="Displays"><facet_maxres label="Resolución máxima (faceta)">1920 x 1080</facet_maxres><facet_scrnsizeus label="Tamaño de pantalla (faceta)">15.6</facet_scrnsizeus></displays><metadata label="Metadata"><facet_prodcat label="Taxonomía (faceta)">Laptops</facet_prodcat><facet_segment label="Segmento (faceta)">Home</facet_segment></metadata><graphic_subsystem label="Graphic Subsystem"><facet_graphics label="Gráficos (faceta)">NVIDIA GeForce</facet_graphics></graphic_subsystem><certification_and_compliance label="Certification and Compliance"><facet_environ label="Medioambiente (faceta)">ENERGY STAR® certified; EPEAT® registered; Low halogen</facet_environ></certification_and_compliance><form_factor label="Form Factor"><facet_formfactor label="Formato (faceta)">Standard laptop</facet_formfactor></form_factor><processor label="Processor"><facet_processortype label="Tipo de procesador (faceta)">Intel Core i7</facet_processortype></processor><features label="Features"><facet_feat label="Recursos (faceta)">Backlit keyboard; BeatsAudio; Bluetooth; Metal chassis; Solid State Drive (SSD); Touchscreen; Wireless Display (WiDi)</facet_feat></features></facets><features><datasheettitlenontrans label="">HP OMEN Notebook</datasheettitlenontrans><ksp_01_suppt_01_short label="">Disfrute incluso de los juegos más exigentes con los gráficos NVIDIA GeForce GTX 860M y un procesador Intel® Core™ i.</ksp_01_suppt_01_short><ksp_02_suppt_01_short label="">Tome el control con un teclado diseñado específicamente para el juego.</ksp_02_suppt_01_short><ksp_03_suppt_01_short label="">Juegue en sus viajes durante horas con un diseño elegante y llamativo, y una duración de la batería optimizada.[9]</ksp_03_suppt_01_short><eco_cs_logo label="ECO CS Logo"><ecohighlighgraphic label="Imagen ECO">http://h10003.www1.hp.com/digmedialib/prodimg/lowres/c03123397.png; http://h10003.www1.hp.com/digmedialib/prodimg/lowres/c03123414.png</ecohighlighgraphic></eco_cs_logo><product_names label="Product Names"><prodbrandname label="Nombre comercial del producto">HP</prodbrandname><proddisplayname label="Nombre de visualización del producto">Notebook HP OMEN</proddisplayname><prodnameshort label="Nombre abreviado del producto">15-5001la</prodnameshort></product_names><limited_messaging_scenarios label="Limited Messaging Scenarios"><ltdproddes_medium label="Descripción general">La PC perfecta, con excelentes características que proporcionan un gran desempeño.</ltdproddes_medium></limited_messaging_scenarios><features_group_1 label="Features Group 1"><feature_01_image_05_name label="Nombre de la imagen de la característica">Teclado con retroiluminación</feature_01_image_05_name><feature_01_image_04_name label="Nombre de la imagen de la característica">Unidad de estado sólido</feature_01_image_04_name><feature_01_image_03_name label="Nombre de la imagen de la característica">Menos de 1 pulg. de grosor</feature_01_image_03_name></features_group_1><key_selling_points label="Key Selling Points"><ksp_02_image_01_url label="URL de imagen de KSP">http://h10003.www1.hp.com/digmedialib/prodimg/lowres/c03795686.png</ksp_02_image_01_url><ksp_03_image_01_url label="URL de imagen de KSP">http://h10003.www1.hp.com/digmedialib/prodimg/lowres/c03795694.png</ksp_03_image_01_url><ksp_03_headline_medium label="Titular">Comience el juego, en cualquier lugar</ksp_03_headline_medium><ksp_02_suppt_01_long label="Argumento clave de venta">Tome el control con un teclado diseñado específicamente para el juego y no perderse ningún movimiento.</ksp_02_suppt_01_long><ksp_01_suppt_01_long label="Argumento clave de venta">Derrote a sus oponentes con un arsenal digno de sus habilidades. Disfrute incluso de los juegos más exigentes con los gráficos de juego NVIDIA GeForce GTX 860M y un procesador Intel® Core™ i de 4ª generación de alto rendimiento.</ksp_01_suppt_01_long><ksp_01_headline_medium label="Titular">Rendimiento del próximo nivel</ksp_01_headline_medium><ksp_02_headline_medium label="Titular">Conquiste su teclado</ksp_02_headline_medium><ksp_03_suppt_01_long label="Argumento clave de venta">Juegue durante horas con más rendimiento y usando menos energía, gracias a la tecnología de optimización de la batería. Elegante y ligero, con la potencia de una desktop, este equipo está listo para ir a cualquier lugar.[9]</ksp_03_suppt_01_long></key_selling_points><eco_quick_links label="ECO Quick Links"><ecoquicklinksbullet_01_url label="01 URL de punto de enlaces rápidos ECO">http://www.hp.com/hpinfo/globalcitizenship/environment/recycling/unwanted-hardware.html</ecoquicklinksbullet_01_url><ecoquicklinksbullet_02_url label="02 URL de punto de enlaces rápidos ECO">http://h71028.www7.hp.com/enterprise/us/en/solutions/hp-carbon-footprint-calculator.html?jumpid=re_r138_eco_home_carbon_footprint_learn_more</ecoquicklinksbullet_02_url><ecoquicklinksbullet_03_url label="03 URL de punto de enlaces rápidos ECO">http://hp.com/environment</ecoquicklinksbullet_03_url><ecoquicklinksbullet_02_url_statement label="Declaración 02 URL de punto de enlaces rápidos ECO">Calculadora de la huella de carbono</ecoquicklinksbullet_02_url_statement><ecoquicklinksbullet_03_url_statement label="Declaración 03 URL de punto de enlaces rápidos ECO">HP y el medio ambiente</ecoquicklinksbullet_03_url_statement><ecoquicklinksbullet_01_url_statement label="Declaración 01 URL de punto de enlaces rápidos ECO">Opciones de reciclaje y reutilización</ecoquicklinksbullet_01_url_statement></eco_quick_links><footnotes label="Footnotes"><msgfootnote_01 label="Nota al pie [01]">[9] La duración de la batería puede variar con el uso.</msgfootnote_01></footnotes></features><special_features><feature_02_suppt_01_medium label="">Maximice su rendimiento con herramientas para comprender la configuración de su sistema y analizar el rendimiento del sistema.</feature_02_suppt_01_medium><feature_01_image_03_url label="">http://h10003.www1.hp.com/digmedialib/prodimg/lowres/c03795694.png</feature_01_image_03_url><feature_01_image_05_url label="">http://h10003.www1.hp.com/digmedialib/prodimg/lowres/c03795690.png</feature_01_image_05_url><feature_01_image_04_url label="">http://h10003.www1.hp.com/digmedialib/prodimg/lowres/c03795783.png</feature_01_image_04_url><feature_02_headline_01_statement label="">HP Performance Advisor</feature_02_headline_01_statement><feature_02_headline_04_statement label="">Wi-Fi rápido</feature_02_headline_04_statement><feature_02_suppt_05_medium label="">Cargue dispositivos incluso en modo de suspensión con HP USB Boost.</feature_02_suppt_05_medium><feature_02_suppt_06_medium label="">Diseño para brindar el audio de mejor calidad disponible en PC.</feature_02_suppt_06_medium><feature_01_headline_05_statement label="">Teclado con retroiluminación</feature_01_headline_05_statement><feature_02_headline_02_statement label="">Cámara web Full HD HP TrueVision</feature_02_headline_02_statement><feature_02_suppt_02_medium label="">Capture todos los detalles con gran claridad, incluso en situaciones de poca luz.</feature_02_suppt_02_medium><feature_01_headline_02_statement label="">Gráficos NVIDIA GeForce GTX</feature_01_headline_02_statement><feature_01_headline_03_statement label="">Diseño elegante</feature_01_headline_03_statement><feature_02_headline_05_statement label="">Encendido</feature_02_headline_05_statement><feature_02_suppt_03_medium label="">Simplifique su vida digital al tener acceso a los archivos de su PC, tablet, teléfono inteligente y servicios en línea, todo en un mismo lugar.[4]</feature_02_suppt_03_medium><feature_02_headline_06_statement label="">BeatsAudio™</feature_02_headline_06_statement><feature_01_headline_06_statement label="">La experiencia NVIDIA GeForce</feature_01_headline_06_statement><feature_01_suppt_05_medium label="">Siga jugando con comodidad incluso en entornos oscuros.</feature_01_suppt_05_medium><feature_02_headline_03_statement label="">Solo en el Reino Unido, Australia, Nueva Zelanda y Estados Unidos: HP Connected Drive</feature_02_headline_03_statement><feature_01_suppt_03_medium label="">Lleve su juego a sus viajes con esta notebook delgada y liviana.</feature_01_suppt_03_medium><feature_01_suppt_02_medium label="">Obtenga gráficos de juegos de vanguardia, multimedios acelerados y mayor duración de la batería con NVIDIA Battery Boost.</feature_01_suppt_02_medium><feature_01_suppt_04_medium label="">Cargue sus juegos con rapidez gracias a las veloces y eficientes unidades de estado sólido de HP.[6]</feature_01_suppt_04_medium><feature_02_suppt_04_medium label="">Conéctese más rápido con mayor alcance mediante conexión inalámbrica de última generación 802.11ac.[5]</feature_02_suppt_04_medium><feature_01_headline_04_statement label="">Unidad de estado sólido HP</feature_01_headline_04_statement><feature_01_suppt_06_medium label="">Actualice sus controladores fácilmente, optimice sus juegos y comparta sus victorias.[3]</feature_01_suppt_06_medium><feature_01_headline_01_statement label="">Pantalla táctil capacitiva Full HD</feature_01_headline_01_statement><feature_01_suppt_01_medium label="">Descubra la auténtica nitidez de una pantalla táctil capacitiva Full HD de 15 pulgadas en diagonal.[1]</feature_01_suppt_01_medium><product_description label="Product Description"><proddes_overview_extended label="Descripción general">Libere sus capacidades con la notebook HP OMEN. Participe de la competencia en cualquier momento y lugar con un equipo para juegos de alto rendimiento que ofrece la potencia de una desktop. Domine a sus oponentes con gráficos impresionantes, una velocidad extraordinaria y sonido envolvente. Agregue recursos personalizables, y es como si la hubiera hecho usted mismo.</proddes_overview_extended><proddes_overview_short label="Descripción general">¡Lo alucinará!</proddes_overview_short><proddes_overview_medium label="Descripción general">Participe de la competencia en cualquier momento y lugar con la notebook HP OMEN, que ofrece la potencia de una desktop. Domine a sus oponentes con gráficos impresionantes, procesamiento a una velocidad extraordinaria, sonido envolvente y características personalizables.</proddes_overview_medium></product_description><legal_information label="Legal Information"><lgldisclaimer_03 label="Exención de responsabilidad legal [03]">[3] Requiere servicio de Internet, no incluido</lgldisclaimer_03><lgldisclaimer_02 label="Exención de responsabilidad legal [02]">[2] No todos los recursos están disponibles en todas las ediciones de Windows 8.1. Los sistemas pueden requerir la actualización o compra por separado de hardware, controladores o software para aprovechar al máximo las funciones de Windows 8.1. Consulte microsoft.com</lgldisclaimer_02><lgldisclaimer_01 label="Exención de responsabilidad legal [01]">[1] Se requiere contenido de alta definición (HD) para visualizar imágenes en alta definición.</lgldisclaimer_01><lgldisclaimer_06 label="Exención de responsabilidad legal [06]">[6] Las unidades de estado sólido (SSD) de 256 GB y 512 GB conectadas con PCle son de 2 a 3 veces más rápidas que las SSD SATA de 128 GB.</lgldisclaimer_06><lgldisclaimer_05 label="Exención de responsabilidad legal [05]">[5] Se necesita un punto de acceso inalámbrico y servicio de Internet, no incluidos. Disponibilidad limitada de puntos de acceso inalámbrico públicos. Se requiere adaptador ethernet USB 3.0, no incluido.</lgldisclaimer_05><lgldisclaimer_04 label="Exención de responsabilidad legal [04]">[4] Compatible con los sistemas operativos Android, Windows e iOS.  Se requiere servicio de Internet, no incluido.</lgldisclaimer_04></legal_information></special_features></content><metadata label="Metadata"><facet_prodcat label="Taxonomía (faceta)">Laptops</facet_prodcat><facet_segment label="Segmento (faceta)">Home</facet_segment></metadata><metadata><upc><content_data>8 88793-88911 4</content_data><description>HP OMEN Notebook PC 15-5001la LTNA - Latin Amer - (120v) Spanish local</description><opt>ABM</opt></upc><market_segments><content_data>hho</content_data><description /><opt /></market_segments><item_publishers /></metadata><plc><blind_date>2014-09-17T00:00:00</blind_date><full_date>2014-11-01T00:00:00</full_date><obsolete_date>2015-12-31T00:00:00</obsolete_date></plc><hierarchy><product_type name="Laptop y Tablet PCs" pmoid="321957" /><marketing_category name="Notebooks HP para el hogar" pmoid="3329744" /><marketing_sub_category name="Notebook para el hogar HP OMEN" pmoid="7280913" /><big_series name="Notebook HP OMEN 15" pmoid="7281264" /><small_series name="Notebook HP OMEN 15-5000" pmoid="7281265" /><model name="Notebook HP OMEN - 15-5001la (ENERGY STAR)" pmoid="7592495" /><sku name="Notebook HP OMEN - 15-5001la (ENERGY STAR)" pmoid="7528760" number="J2M88LA" /></hierarchy><links><link type="child"><pmoid>5367968</pmoid><num>NW281AA</num><name>HP Classroom Manager 2.0</name><type>Accessories</type><order>0</order><reco>0</reco><full_date>2013-04-17T00:00:00</full_date><obsolete_date>2019-04-30T00:00:00</obsolete_date><marketing_sub_category pmoid="5363258">Software de formación</marketing_sub_category><marketing_category pmoid="4249944">Software de formación</marketing_category><product_type pmoid="18964">Software</product_type></link><link type="child"><pmoid>5246564</pmoid><num>H2C22AA</num><name>Mouse inalámbrico HP X3000</name><type>Accessories</type><order>0</order><reco>0</reco><full_date>2012-10-01T00:00:00</full_date><obsolete_date>2017-03-31T00:00:00</obsolete_date><marketing_sub_category pmoid="329251">Mouse</marketing_sub_category><marketing_category pmoid="69998">Teclados/ratones/monitores y dispositivos de entrada</marketing_category><product_type pmoid="329290">Opciones y Accesorios</product_type></link><link type="child"><pmoid>5438161</pmoid><num>E5J19AA</num><name>Mouse inalámbrico blanco HP Z3200</name><type>Accessories</type><order>0</order><reco>0</reco><full_date>2014-02-01T00:00:00</full_date><obsolete_date>2015-11-30T00:00:00</obsolete_date><marketing_sub_category pmoid="329251">Mouse</marketing_sub_category><marketing_category pmoid="69998">Teclados/ratones/monitores y dispositivos de entrada</marketing_category><product_type pmoid="329290">Opciones y Accesorios</product_type></link><link type="child"><pmoid>5438158</pmoid><num>E5J20AA</num><name>Mouse inalámbrico plateado HP Z3200</name><type>Accessories</type><order>0</order><reco>0</reco><full_date>2014-02-01T00:00:00</full_date><obsolete_date>2015-11-30T00:00:00</obsolete_date><marketing_sub_category pmoid="329251">Mouse</marketing_sub_category><marketing_category pmoid="69998">Teclados/ratones/monitores y dispositivos de entrada</marketing_category><product_type pmoid="329290">Opciones y Accesorios</product_type></link><link type="child"><pmoid>6929520</pmoid><num>G6H44AA</num><name>Adaptador de CA inteligente de 120W de HP</name><type>Accessories</type><order>0</order><reco>0</reco><full_date>2014-04-14T00:00:00</full_date><obsolete_date>2016-07-31T00:00:00</obsolete_date><marketing_sub_category pmoid="329261">Adaptadores de CA</marketing_sub_category><marketing_category pmoid="329223">Baterías/cargadores/adaptadores</marketing_category><product_type pmoid="329290">Opciones y Accesorios</product_type></link><link type="child"><pmoid>6356169</pmoid><num>H7B00AA</num><name>Mouse inalámbrico HP Z3600 Pink</name><type>Accessories</type><order>0</order><reco>0</reco><full_date>2014-02-01T00:00:00</full_date><obsolete_date>2016-08-31T00:00:00</obsolete_date><marketing_sub_category pmoid="329251">Mouse</marketing_sub_category><marketing_category pmoid="69998">Teclados/ratones/monitores y dispositivos de entrada</marketing_category><product_type pmoid="329290">Opciones y Accesorios</product_type></link><link type="child"><pmoid>7183833</pmoid><num>J6N88AA</num><name>Mouse OMEN para HP X9000</name><type>Accessories</type><order>0</order><reco>0</reco><full_date>2014-11-04T00:00:00</full_date><obsolete_date>2017-12-31T00:00:00</obsolete_date><marketing_sub_category pmoid="329251">Mouse</marketing_sub_category><marketing_category pmoid="69998">Teclados/ratones/monitores y dispositivos de entrada</marketing_category><product_type pmoid="329290">Opciones y Accesorios</product_type></link><link type="child"><pmoid>6258842</pmoid><num>F3W20AA</num><name>Mochila Empire HP 14.1</name><type>Accessories</type><order>0</order><reco>0</reco><full_date>2013-11-01T00:00:00</full_date><obsolete_date>2016-01-31T00:00:00</obsolete_date><marketing_sub_category pmoid="3965879">Mochilas</marketing_sub_category><marketing_category pmoid="70657">Maletines y Cubiertas</marketing_category><product_type pmoid="329290">Opciones y Accesorios</product_type></link><link type="child"><pmoid>1157007</pmoid><num>HC347PE</num><name>1 año de servicio HP postgarantía de soporte telefónico solamente para personal de computadoras</name><type>Services</type><order>99</order><reco>0</reco><full_date>2005-09-01T00:00:00</full_date><obsolete_date>2099-04-01T00:00:00</obsolete_date><marketing_sub_category pmoid="80934">Servicios de soporte de hardware</marketing_sub_category><marketing_category pmoid="449130">Servicios de Tecnología</marketing_category><product_type pmoid="22744">Servicios</product_type></link><link type="child"><pmoid>4016257</pmoid><num>UM931E</num><name>HP Care Pack 3 años, Retorno a HP para Pavilion Notebook</name><type>Services</type><order>4</order><reco>0</reco><full_date>2012-11-01T00:00:00</full_date><obsolete_date>2019-08-01T00:00:00</obsolete_date><marketing_sub_category pmoid="80934">Servicios de soporte de hardware</marketing_sub_category><marketing_category pmoid="449130">Servicios de Tecnología</marketing_category><product_type pmoid="22744">Servicios</product_type></link><link type="child"><pmoid>4016251</pmoid><num>UM928E</num><name>HP Care Pack 2 años, Retorno a HP para Pavilion Notebook</name><type>Services</type><order>97</order><reco>0</reco><full_date>2012-11-01T00:00:00</full_date><obsolete_date>2019-08-01T00:00:00</obsolete_date><marketing_sub_category pmoid="80934">Servicios de soporte de hardware</marketing_sub_category><marketing_category pmoid="449130">Servicios de Tecnología</marketing_category><product_type pmoid="22744">Servicios</product_type></link><link type="child"><pmoid>4016226</pmoid><num>UM936E</num><name>Servicio HP para notebook de protección contra daños accidentales más devolución al depósito por 3 años con 2 años de garantía</name><type>Services</type><order>97</order><reco>0</reco><full_date>2012-11-01T00:00:00</full_date><obsolete_date>2019-08-01T00:00:00</obsolete_date><marketing_sub_category pmoid="80934">Servicios de soporte de hardware</marketing_sub_category><marketing_category pmoid="449130">Servicios de Tecnología</marketing_category><product_type pmoid="22744">Servicios</product_type></link><link type="child"><pmoid>4087776</pmoid><num>UM969E</num><name>Servicio HP para notebook de protección contra daños accidentales más recogida y devolución por 1 año</name><type>Services</type><order>97</order><reco>0</reco><full_date>2012-11-01T00:00:00</full_date><obsolete_date>2020-02-01T00:00:00</obsolete_date><marketing_sub_category pmoid="80934">Servicios de soporte de hardware</marketing_sub_category><marketing_category pmoid="449130">Servicios de Tecnología</marketing_category><product_type pmoid="22744">Servicios</product_type></link><link type="child"><pmoid>4090158</pmoid><num>UM993PE</num><name>Servicio HP posgarantía para notebook de devolución al depósito por 1 año</name><type>Services</type><order>99</order><reco>0</reco><full_date>2012-11-01T00:00:00</full_date><obsolete_date>2020-02-01T00:00:00</obsolete_date><marketing_sub_category pmoid="80934">Servicios de soporte de hardware</marketing_sub_category><marketing_category pmoid="449130">Servicios de Tecnología</marketing_category><product_type pmoid="22744">Servicios</product_type></link><link type="child"><pmoid>4087870</pmoid><num>UM971E</num><name>Servicio HP para notebook de protección contra daños accidentales y recogida y devolución por 4 años</name><type>Services</type><order>97</order><reco>0</reco><full_date>2012-11-01T00:00:00</full_date><obsolete_date>2020-02-01T00:00:00</obsolete_date><marketing_sub_category pmoid="80934">Servicios de soporte de hardware</marketing_sub_category><marketing_category pmoid="449130">Servicios de Tecnología</marketing_category><product_type pmoid="22744">Servicios</product_type></link></links><images><image><cmg_acronym>cmg518</cmg_acronym><master_object_name>c04537743</master_object_name><content_type>png</content_type><image_url_https>https://h10003.www1.hp.com/digmedialib/prodimg/lowres/c04537745.png</image_url_https><pixel_height>41</pixel_height><file_name>c04537745.png</file_name><orientation>Right facing</orientation><pixel_width>54</pixel_width><action>touch</action><image_url_http>http://h10003.www1.hp.com/digmedialib/prodimg/lowres/c04537745.png</image_url_http><background>Transparent</background><full_title>HP OMEN 15-5000 Notebook PC</full_title><document_type_detail>product image - not as shown</document_type_detail><document_type>web standard graphic</document_type><dpi_resolution>72</dpi_resolution></image><image><cmg_acronym>cmg518</cmg_acronym><master_object_name>c04537784</master_object_name><content_type>png</content_type><image_url_https>https://h10003.www1.hp.com/digmedialib/prodimg/lowres/c04537788.png</image_url_https><pixel_height>135</pixel_height><file_name>c04537788.png</file_name><orientation>Left facing</orientation><pixel_width>180</pixel_width><action>touch</action><image_url_http>http://h10003.www1.hp.com/digmedialib/prodimg/lowres/c04537788.png</image_url_http><background>Transparent</background><full_title>HP OMEN 15-5000 Notebook PC</full_title><document_type_detail>product image - not as shown</document_type_detail><document_type>web standard graphic</document_type><dpi_resolution>72</dpi_resolution></image><image><cmg_acronym>cmg518</cmg_acronym><master_object_name>c04537696</master_object_name><content_type>png</content_type><image_url_https>https://h10003.www1.hp.com/digmedialib/prodimg/lowres/c04537705.png</image_url_https><pixel_height>193</pixel_height><file_name>c04537705.png</file_name><orientation>Center facing</orientation><pixel_width>257</pixel_width><action>touch</action><image_url_http>http://h10003.www1.hp.com/digmedialib/prodimg/lowres/c04537705.png</image_url_http><background>Transparent</background><full_title>HP OMEN 15-5000 Notebook PC</full_title><document_type_detail>product image - not as shown</document_type_detail><document_type>web standard graphic</document_type><dpi_resolution>72</dpi_resolution></image><image><cmg_acronym>cmg518</cmg_acronym><master_object_name>c04537851</master_object_name><content_type>png</content_type><image_url_https>https://h10003.www1.hp.com/digmedialib/prodimg/lowres/c04537865.png</image_url_https><pixel_height>72</pixel_height><file_name>c04537865.png</file_name><orientation>Left rear facing</orientation><pixel_width>96</pixel_width><action>touch</action><image_url_http>http://h10003.www1.hp.com/digmedialib/prodimg/lowres/c04537865.png</image_url_http><background>Transparent</background><full_title>HP OMEN 15-5000 Notebook PC</full_title><document_type_detail>product image - not as shown</document_type_detail><document_type>web standard graphic</document_type><dpi_resolution>72</dpi_resolution></image><image><cmg_acronym>cmg518</cmg_acronym><master_object_name>c04537696</master_object_name><content_type>png</content_type><image_url_https>https://h10003.www1.hp.com/digmedialib/prodimg/lowres/c04537702.png</image_url_https><pixel_height>72</pixel_height><file_name>c04537702.png</file_name><orientation>Center facing</orientation><pixel_width>96</pixel_width><action>touch</action><image_url_http>http://h10003.www1.hp.com/digmedialib/prodimg/lowres/c04537702.png</image_url_http><background>Transparent</background><full_title>HP OMEN 15-5000 Notebook PC</full_title><document_type_detail>product image - not as shown</document_type_detail><document_type>web standard graphic</document_type><dpi_resolution>72</dpi_resolution></image><image><cmg_acronym>cmg518</cmg_acronym><master_object_name>c04537851</master_object_name><content_type>png</content_type><image_url_https>https://h10003.www1.hp.com/digmedialib/prodimg/lowres/c04537858.png</image_url_https><pixel_height>430</pixel_height><file_name>c04537858.png</file_name><orientation>Left rear facing</orientation><pixel_width>573</pixel_width><action>touch</action><image_url_http>http://h10003.www1.hp.com/digmedialib/prodimg/lowres/c04537858.png</image_url_http><background>Transparent</background><full_title>HP OMEN 15-5000 Notebook PC</full_title><document_type_detail>product image - not as shown</document_type_detail><document_type>web standard graphic</document_type><dpi_resolution>72</dpi_resolution></image><image><cmg_acronym>cmg518</cmg_acronym><master_object_name>c04537784</master_object_name><content_type>jpg</content_type><image_url_https>https://h10003.www1.hp.com/digmedialib/prodimg/lowres/c04537791.jpg</image_url_https><pixel_height>240</pixel_height><file_name>c04537791.jpg</file_name><orientation>Left facing</orientation><pixel_width>320</pixel_width><action>touch</action><image_url_http>http://h10003.www1.hp.com/digmedialib/prodimg/lowres/c04537791.jpg</image_url_http><background>White</background><full_title>HP OMEN 15-5000 Notebook PC</full_title><document_type_detail>product image - not as shown</document_type_detail><document_type>web standard graphic</document_type><dpi_resolution>72</dpi_resolution></image><image><cmg_acronym>cmg518</cmg_acronym><master_object_name>c04537743</master_object_name><content_type>jpg</content_type><image_url_https>https://h10003.www1.hp.com/digmedialib/prodimg/lowres/c04537759.jpg</image_url_https><pixel_height>180</pixel_height><file_name>c04537759.jpg</file_name><orientation>Right facing</orientation><pixel_width>240</pixel_width><action>touch</action><image_url_http>http://h10003.www1.hp.com/digmedialib/prodimg/lowres/c04537759.jpg</image_url_http><background>White</background><full_title>HP OMEN 15-5000 Notebook PC</full_title><document_type_detail>product image - not as shown</document_type_detail><document_type>web standard graphic</document_type><dpi_resolution>72</dpi_resolution></image><image><cmg_acronym>cmg518</cmg_acronym><master_object_name>c04537851</master_object_name><content_type>png</content_type><image_url_https>https://h10003.www1.hp.com/digmedialib/prodimg/lowres/c04537862.png</image_url_https><pixel_height>356</pixel_height><file_name>c04537862.png</file_name><orientation>Left rear facing</orientation><pixel_width>474</pixel_width><action>touch</action><image_url_http>http://h10003.www1.hp.com/digmedialib/prodimg/lowres/c04537862.png</image_url_http><background>Transparent</background><full_title>HP OMEN 15-5000 Notebook PC</full_title><document_type_detail>product image - not as shown</document_type_detail><document_type>web standard graphic</document_type><dpi_resolution>72</dpi_resolution></image><image><cmg_acronym>cmg518</cmg_acronym><master_object_name>c04537851</master_object_name><content_type>jpg</content_type><image_url_https>https://h10003.www1.hp.com/digmedialib/prodimg/lowres/c04537867.jpg</image_url_https><pixel_height>72</pixel_height><file_name>c04537867.jpg</file_name><orientation>Left rear facing</orientation><pixel_width>96</pixel_width><action>touch</action><image_url_http>http://h10003.www1.hp.com/digmedialib/prodimg/lowres/c04537867.jpg</image_url_http><background>White</background><full_title>HP OMEN 15-5000 Notebook PC</full_title><document_type_detail>product image - not as shown</document_type_detail><document_type>web standard graphic</document_type><dpi_resolution>72</dpi_resolution></image><image><cmg_acronym>cmg518</cmg_acronym><master_object_name>c04537743</master_object_name><content_type>png</content_type><image_url_https>https://h10003.www1.hp.com/digmedialib/prodimg/lowres/c04537753.png</image_url_https><pixel_height>430</pixel_height><file_name>c04537753.png</file_name><orientation>Right facing</orientation><pixel_width>573</pixel_width><action>touch</action><image_url_http>http://h10003.www1.hp.com/digmedialib/prodimg/lowres/c04537753.png</image_url_http><background>Transparent</background><full_title>HP OMEN 15-5000 Notebook PC</full_title><document_type_detail>product image - not as shown</document_type_detail><document_type>web standard graphic</document_type><dpi_resolution>72</dpi_resolution></image><image><cmg_acronym>cmg518</cmg_acronym><master_object_name>c04537851</master_object_name><content_type>png</content_type><image_url_https>https://h10003.www1.hp.com/digmedialib/prodimg/lowres/c04537863.png</image_url_https><pixel_height>240</pixel_height><file_name>c04537863.png</file_name><orientation>Left rear facing</orientation><pixel_width>320</pixel_width><action>touch</action><image_url_http>http://h10003.www1.hp.com/digmedialib/prodimg/lowres/c04537863.png</image_url_http><background>Transparent</background><full_title>HP OMEN 15-5000 Notebook PC</full_title><document_type_detail>product image - not as shown</document_type_detail><document_type>web standard graphic</document_type><dpi_resolution>72</dpi_resolution></image><image><cmg_acronym>cmg518</cmg_acronym><master_object_name>c04537784</master_object_name><content_type>png</content_type><image_url_https>https://h10003.www1.hp.com/digmedialib/prodimg/lowres/c04537792.png</image_url_https><pixel_height>74</pixel_height><file_name>c04537792.png</file_name><orientation>Left facing</orientation><pixel_width>99</pixel_width><action>touch</action><image_url_http>http://h10003.www1.hp.com/digmedialib/prodimg/lowres/c04537792.png</image_url_http><background>Transparent</background><full_title>HP OMEN 15-5000 Notebook PC</full_title><document_type_detail>product image - not as shown</document_type_detail><document_type>web standard graphic</document_type><dpi_resolution>72</dpi_resolution></image><image><cmg_acronym>cmg518</cmg_acronym><master_object_name>c04537851</master_object_name><content_type>jpg</content_type><image_url_https>https://h10003.www1.hp.com/digmedialib/prodimg/lowres/c04537856.jpg</image_url_https><pixel_height>41</pixel_height><file_name>c04537856.jpg</file_name><orientation>Left rear facing</orientation><pixel_width>54</pixel_width><action>touch</action><image_url_http>http://h10003.www1.hp.com/digmedialib/prodimg/lowres/c04537856.jpg</image_url_http><background>White</background><full_title>HP OMEN 15-5000 Notebook PC</full_title><document_type_detail>product image - not as shown</document_type_detail><document_type>web standard graphic</document_type><dpi_resolution>72</dpi_resolution></image><image><cmg_acronym>cmg518</cmg_acronym><master_object_name>c04537851</master_object_name><content_type>jpg</content_type><image_url_https>https://h10003.www1.hp.com/digmedialib/prodimg/lowres/c04537854.jpg</image_url_https><pixel_height>180</pixel_height><file_name>c04537854.jpg</file_name><orientation>Left rear facing</orientation><pixel_width>240</pixel_width><action>touch</action><image_url_http>http://h10003.www1.hp.com/digmedialib/prodimg/lowres/c04537854.jpg</image_url_http><background>White</background><full_title>HP OMEN 15-5000 Notebook PC</full_title><document_type_detail>product image - not as shown</document_type_detail><document_type>web standard graphic</document_type><dpi_resolution>72</dpi_resolution></image><image><cmg_acronym>cmg518</cmg_acronym><master_object_name>c04537743</master_object_name><content_type>png</content_type><image_url_https>https://h10003.www1.hp.com/digmedialib/prodimg/lowres/c04537744.png</image_url_https><pixel_height>356</pixel_height><file_name>c04537744.png</file_name><orientation>Right facing</orientation><pixel_width>474</pixel_width><action>touch</action><image_url_http>http://h10003.www1.hp.com/digmedialib/prodimg/lowres/c04537744.png</image_url_http><background>Transparent</background><full_title>HP OMEN 15-5000 Notebook PC</full_title><document_type_detail>product image - not as shown</document_type_detail><document_type>web standard graphic</document_type><dpi_resolution>72</dpi_resolution></image><image><cmg_acronym>cmg518</cmg_acronym><master_object_name>c04537743</master_object_name><content_type>png</content_type><image_url_https>https://h10003.www1.hp.com/digmedialib/prodimg/lowres/c04537746.png</image_url_https><pixel_height>240</pixel_height><file_name>c04537746.png</file_name><orientation>Right facing</orientation><pixel_width>320</pixel_width><action>touch</action><image_url_http>http://h10003.www1.hp.com/digmedialib/prodimg/lowres/c04537746.png</image_url_http><background>Transparent</background><full_title>HP OMEN 15-5000 Notebook PC</full_title><document_type_detail>product image - not as shown</document_type_detail><document_type>web standard graphic</document_type><dpi_resolution>72</dpi_resolution></image><image><cmg_acronym>cmg518</cmg_acronym><master_object_name>c04537784</master_object_name><content_type>jpg</content_type><image_url_https>https://h10003.www1.hp.com/digmedialib/prodimg/lowres/c04537794.jpg</image_url_https><pixel_height>41</pixel_height><file_name>c04537794.jpg</file_name><orientation>Left facing</orientation><pixel_width>54</pixel_width><action>touch</action><image_url_http>http://h10003.www1.hp.com/digmedialib/prodimg/lowres/c04537794.jpg</image_url_http><background>White</background><full_title>HP OMEN 15-5000 Notebook PC</full_title><document_type_detail>product image - not as shown</document_type_detail><document_type>web standard graphic</document_type><dpi_resolution>72</dpi_resolution></image><image><cmg_acronym>cmg518</cmg_acronym><master_object_name>c04537696</master_object_name><content_type>png</content_type><image_url_https>https://h10003.www1.hp.com/digmedialib/prodimg/lowres/c04537712.png</image_url_https><pixel_height>135</pixel_height><file_name>c04537712.png</file_name><orientation>Center facing</orientation><pixel_width>180</pixel_width><action>touch</action><image_url_http>http://h10003.www1.hp.com/digmedialib/prodimg/lowres/c04537712.png</image_url_http><background>Transparent</background><full_title>HP OMEN 15-5000 Notebook PC</full_title><document_type_detail>product image - not as shown</document_type_detail><document_type>web standard graphic</document_type><dpi_resolution>72</dpi_resolution></image><image><cmg_acronym>cmg518</cmg_acronym><master_object_name>c04537696</master_object_name><content_type>png</content_type><image_url_https>https://h10003.www1.hp.com/digmedialib/prodimg/lowres/c04537706.png</image_url_https><pixel_height>115</pixel_height><file_name>c04537706.png</file_name><orientation>Center facing</orientation><pixel_width>153</pixel_width><action>touch</action><image_url_http>http://h10003.www1.hp.com/digmedialib/prodimg/lowres/c04537706.png</image_url_http><background>Transparent</background><full_title>HP OMEN 15-5000 Notebook PC</full_title><document_type_detail>product image - not as shown</document_type_detail><document_type>web standard graphic</document_type><dpi_resolution>72</dpi_resolution></image><image><cmg_acronym>cmg518</cmg_acronym><master_object_name>c04537696</master_object_name><content_type>png</content_type><image_url_https>https://h10003.www1.hp.com/digmedialib/prodimg/lowres/c04537703.png</image_url_https><pixel_height>185</pixel_height><file_name>c04537703.png</file_name><orientation>Center facing</orientation><pixel_width>247</pixel_width><action>touch</action><image_url_http>http://h10003.www1.hp.com/digmedialib/prodimg/lowres/c04537703.png</image_url_http><background>Transparent</background><full_title>HP OMEN 15-5000 Notebook PC</full_title><document_type_detail>product image - not as shown</document_type_detail><document_type>web standard graphic</document_type><dpi_resolution>72</dpi_resolution></image><image><cmg_acronym>cmg518</cmg_acronym><master_object_name>c04537743</master_object_name><content_type>png</content_type><image_url_https>https://h10003.www1.hp.com/digmedialib/prodimg/lowres/c04537749.png</image_url_https><pixel_height>385</pixel_height><file_name>c04537749.png</file_name><orientation>Right facing</orientation><pixel_width>513</pixel_width><action>touch</action><image_url_http>http://h10003.www1.hp.com/digmedialib/prodimg/lowres/c04537749.png</image_url_http><background>Transparent</background><full_title>HP OMEN 15-5000 Notebook PC</full_title><document_type_detail>product image - not as shown</document_type_detail><document_type>web standard graphic</document_type><dpi_resolution>72</dpi_resolution></image><image><cmg_acronym>cmg518</cmg_acronym><master_object_name>c04372191</master_object_name><content_type>png</content_type><image_url_https>https://h10003.www1.hp.com/digmedialib/prodimg/lowres/c04372205.png</image_url_https><pixel_height>72</pixel_height><file_name>c04372205.png</file_name><orientation>Left rear facing</orientation><pixel_width>96</pixel_width><action>touch</action><image_url_http>http://h10003.www1.hp.com/digmedialib/prodimg/lowres/c04372205.png</image_url_http><background>Transparent</background><full_title>HP OMEN 15-5000 Notebook PC</full_title><document_type_detail>product image - not as shown</document_type_detail><document_type>web standard graphic</document_type><dpi_resolution>72</dpi_resolution></image><image><cmg_acronym>cmg518</cmg_acronym><master_object_name>c04372171</master_object_name><content_type>png</content_type><image_url_https>https://h10003.www1.hp.com/digmedialib/prodimg/lowres/c04372189.png</image_url_https><pixel_height>240</pixel_height><file_name>c04372189.png</file_name><orientation>Rear facing</orientation><pixel_width>320</pixel_width><action>touch</action><image_url_http>http://h10003.www1.hp.com/digmedialib/prodimg/lowres/c04372189.png</image_url_http><background>Transparent</background><full_title>HP OMEN 15-5000 Notebook PC</full_title><document_type_detail>product image - not as shown</document_type_detail><document_type>web standard graphic</document_type><dpi_resolution>72</dpi_resolution></image><image><cmg_acronym>cmg518</cmg_acronym><master_object_name>c04372171</master_object_name><content_type>png</content_type><image_url_https>https://h10003.www1.hp.com/digmedialib/prodimg/lowres/c04372185.png</image_url_https><pixel_height>193</pixel_height><file_name>c04372185.png</file_name><orientation>Rear facing</orientation><pixel_width>257</pixel_width><action>touch</action><image_url_http>http://h10003.www1.hp.com/digmedialib/prodimg/lowres/c04372185.png</image_url_http><background>Transparent</background><full_title>HP OMEN 15-5000 Notebook PC</full_title><document_type_detail>product image - not as shown</document_type_detail><document_type>web standard graphic</document_type><dpi_resolution>72</dpi_resolution></image><image><cmg_acronym>cmg518</cmg_acronym><master_object_name>c04372171</master_object_name><content_type>png</content_type><image_url_https>https://h10003.www1.hp.com/digmedialib/prodimg/lowres/c04372190.png</image_url_https><pixel_height>74</pixel_height><file_name>c04372190.png</file_name><orientation>Rear facing</orientation><pixel_width>99</pixel_width><action>touch</action><image_url_http>http://h10003.www1.hp.com/digmedialib/prodimg/lowres/c04372190.png</image_url_http><background>Transparent</background><full_title>HP OMEN 15-5000 Notebook PC</full_title><document_type_detail>product image - not as shown</document_type_detail><document_type>web standard graphic</document_type><dpi_resolution>72</dpi_resolution></image><image><cmg_acronym>cmg518</cmg_acronym><master_object_name>c04372171</master_object_name><content_type>png</content_type><image_url_https>https://h10003.www1.hp.com/digmedialib/prodimg/lowres/c04372181.png</image_url_https><pixel_height>115</pixel_height><file_name>c04372181.png</file_name><orientation>Rear facing</orientation><pixel_width>153</pixel_width><action>touch</action><image_url_http>http://h10003.www1.hp.com/digmedialib/prodimg/lowres/c04372181.png</image_url_http><background>Transparent</background><full_title>HP OMEN 15-5000 Notebook PC</full_title><document_type_detail>product image - not as shown</document_type_detail><document_type>web standard graphic</document_type><dpi_resolution>72</dpi_resolution></image><image><cmg_acronym>cmg518</cmg_acronym><master_object_name>c04372171</master_object_name><content_type>png</content_type><image_url_https>https://h10003.www1.hp.com/digmedialib/prodimg/lowres/c04372188.png</image_url_https><pixel_height>72</pixel_height><file_name>c04372188.png</file_name><orientation>Rear facing</orientation><pixel_width>96</pixel_width><action>touch</action><image_url_http>http://h10003.www1.hp.com/digmedialib/prodimg/lowres/c04372188.png</image_url_http><background>Transparent</background><full_title>HP OMEN 15-5000 Notebook PC</full_title><document_type_detail>product image - not as shown</document_type_detail><document_type>web standard graphic</document_type><dpi_resolution>72</dpi_resolution></image><image><cmg_acronym>cmg518</cmg_acronym><master_object_name>c04372171</master_object_name><content_type>jpg</content_type><image_url_https>https://h10003.www1.hp.com/digmedialib/prodimg/lowres/c04372179.jpg</image_url_https><pixel_height>41</pixel_height><file_name>c04372179.jpg</file_name><orientation>Rear facing</orientation><pixel_width>54</pixel_width><action>touch</action><image_url_http>http://h10003.www1.hp.com/digmedialib/prodimg/lowres/c04372179.jpg</image_url_http><background>White</background><full_title>HP OMEN 15-5000 Notebook PC</full_title><document_type_detail>product image - not as shown</document_type_detail><document_type>web standard graphic</document_type><dpi_resolution>72</dpi_resolution></image><image><cmg_acronym>cmg518</cmg_acronym><master_object_name>c04372171</master_object_name><content_type>png</content_type><image_url_https>https://h10003.www1.hp.com/digmedialib/prodimg/lowres/c04372178.png</image_url_https><pixel_height>385</pixel_height><file_name>c04372178.png</file_name><orientation>Rear facing</orientation><pixel_width>513</pixel_width><action>touch</action><image_url_http>http://h10003.www1.hp.com/digmedialib/prodimg/lowres/c04372178.png</image_url_http><background>Transparent</background><full_title>HP OMEN 15-5000 Notebook PC</full_title><document_type_detail>product image - not as shown</document_type_detail><document_type>web standard graphic</document_type><dpi_resolution>72</dpi_resolution></image><image><cmg_acronym>cmg518</cmg_acronym><master_object_name>c04372171</master_object_name><content_type>jpg</content_type><image_url_https>https://h10003.www1.hp.com/digmedialib/prodimg/lowres/c04372183.jpg</image_url_https><pixel_height>180</pixel_height><file_name>c04372183.jpg</file_name><orientation>Rear facing</orientation><pixel_width>240</pixel_width><action>touch</action><image_url_http>http://h10003.www1.hp.com/digmedialib/prodimg/lowres/c04372183.jpg</image_url_http><background>White</background><full_title>HP OMEN 15-5000 Notebook PC</full_title><document_type_detail>product image - not as shown</document_type_detail><document_type>web standard graphic</document_type><dpi_resolution>72</dpi_resolution></image><image><cmg_acronym>cmg518</cmg_acronym><master_object_name>c04372171</master_object_name><content_type>png</content_type><image_url_https>https://h10003.www1.hp.com/digmedialib/prodimg/lowres/c04372187.png</image_url_https><pixel_height>185</pixel_height><file_name>c04372187.png</file_name><orientation>Rear facing</orientation><pixel_width>247</pixel_width><action>touch</action><image_url_http>http://h10003.www1.hp.com/digmedialib/prodimg/lowres/c04372187.png</image_url_http><background>Transparent</background><full_title>HP OMEN 15-5000 Notebook PC</full_title><document_type_detail>product image - not as shown</document_type_detail><document_type>web standard graphic</document_type><dpi_resolution>72</dpi_resolution></image><image><cmg_acronym>cmg518</cmg_acronym><master_object_name>c04372171</master_object_name><content_type>png</content_type><image_url_https>https://h10003.www1.hp.com/digmedialib/prodimg/lowres/c04372172.png</image_url_https><pixel_height>430</pixel_height><file_name>c04372172.png</file_name><orientation>Rear facing</orientation><pixel_width>573</pixel_width><action>touch</action><image_url_http>http://h10003.www1.hp.com/digmedialib/prodimg/lowres/c04372172.png</image_url_http><background>Transparent</background><full_title>HP OMEN 15-5000 Notebook PC</full_title><document_type_detail>product image - not as shown</document_type_detail><document_type>web standard graphic</document_type><dpi_resolution>72</dpi_resolution></image><image><cmg_acronym>cmg518</cmg_acronym><master_object_name>c04372171</master_object_name><content_type>jpg</content_type><image_url_https>https://h10003.www1.hp.com/digmedialib/prodimg/lowres/c04372184.jpg</image_url_https><pixel_height>240</pixel_height><file_name>c04372184.jpg</file_name><orientation>Rear facing</orientation><pixel_width>320</pixel_width><action>touch</action><image_url_http>http://h10003.www1.hp.com/digmedialib/prodimg/lowres/c04372184.jpg</image_url_http><background>White</background><full_title>HP OMEN 15-5000 Notebook PC</full_title><document_type_detail>product image - not as shown</document_type_detail><document_type>web standard graphic</document_type><dpi_resolution>72</dpi_resolution></image><image><cmg_acronym>cmg518</cmg_acronym><master_object_name>c04372171</master_object_name><content_type>png</content_type><image_url_https>https://h10003.www1.hp.com/digmedialib/prodimg/lowres/c04372182.png</image_url_https><pixel_height>356</pixel_height><file_name>c04372182.png</file_name><orientation>Rear facing</orientation><pixel_width>474</pixel_width><action>touch</action><image_url_http>http://h10003.www1.hp.com/digmedialib/prodimg/lowres/c04372182.png</image_url_http><background>Transparent</background><full_title>HP OMEN 15-5000 Notebook PC</full_title><document_type_detail>product image - not as shown</document_type_detail><document_type>web standard graphic</document_type><dpi_resolution>72</dpi_resolution></image><image><cmg_acronym>cmg518</cmg_acronym><master_object_name>c04372171</master_object_name><content_type>png</content_type><image_url_https>https://h10003.www1.hp.com/digmedialib/prodimg/lowres/c04372171.png</image_url_https><pixel_height>2315</pixel_height><file_name>c04372171.png</file_name><orientation>Rear facing</orientation><pixel_width>3300</pixel_width><action>touch</action><image_url_http>http://h10003.www1.hp.com/digmedialib/prodimg/lowres/c04372171.png</image_url_http><background>Transparent</background><full_title>HP OMEN 15-5000 Notebook PC</full_title><document_type_detail>product image - not as shown</document_type_detail><document_type>web standard graphic</document_type><dpi_resolution>300</dpi_resolution></image><image><cmg_acronym>cmg518</cmg_acronym><master_object_name>c04372171</master_object_name><content_type>png</content_type><image_url_https>https://h10003.www1.hp.com/digmedialib/prodimg/lowres/c04372173.png</image_url_https><pixel_height>41</pixel_height><file_name>c04372173.png</file_name><orientation>Rear facing</orientation><pixel_width>54</pixel_width><action>touch</action><image_url_http>http://h10003.www1.hp.com/digmedialib/prodimg/lowres/c04372173.png</image_url_http><background>Transparent</background><full_title>HP OMEN 15-5000 Notebook PC</full_title><document_type_detail>product image - not as shown</document_type_detail><document_type>web standard graphic</document_type><dpi_resolution>72</dpi_resolution></image><image><cmg_acronym>cmg518</cmg_acronym><master_object_name>c04372171</master_object_name><content_type>png</content_type><image_url_https>https://h10003.www1.hp.com/digmedialib/prodimg/lowres/c04372186.png</image_url_https><pixel_height>180</pixel_height><file_name>c04372186.png</file_name><orientation>Rear facing</orientation><pixel_width>240</pixel_width><action>touch</action><image_url_http>http://h10003.www1.hp.com/digmedialib/prodimg/lowres/c04372186.png</image_url_http><background>Transparent</background><full_title>HP OMEN 15-5000 Notebook PC</full_title><document_type_detail>product image - not as shown</document_type_detail><document_type>web standard graphic</document_type><dpi_resolution>72</dpi_resolution></image><image><cmg_acronym>cmg518</cmg_acronym><master_object_name>c04372171</master_object_name><content_type>png</content_type><image_url_https>https://h10003.www1.hp.com/digmedialib/prodimg/lowres/c04372177.png</image_url_https><pixel_height>135</pixel_height><file_name>c04372177.png</file_name><orientation>Rear facing</orientation><pixel_width>180</pixel_width><action>touch</action><image_url_http>http://h10003.www1.hp.com/digmedialib/prodimg/lowres/c04372177.png</image_url_http><background>Transparent</background><full_title>HP OMEN 15-5000 Notebook PC</full_title><document_type_detail>product image - not as shown</document_type_detail><document_type>web standard graphic</document_type><dpi_resolution>72</dpi_resolution></image><image><cmg_acronym>cmg518</cmg_acronym><master_object_name>c04372171</master_object_name><content_type>jpg</content_type><image_url_https>https://h10003.www1.hp.com/digmedialib/prodimg/lowres/c04372180.jpg</image_url_https><pixel_height>72</pixel_height><file_name>c04372180.jpg</file_name><orientation>Rear facing</orientation><pixel_width>96</pixel_width><action>touch</action><image_url_http>http://h10003.www1.hp.com/digmedialib/prodimg/lowres/c04372180.jpg</image_url_http><background>White</background><full_title>HP OMEN 15-5000 Notebook PC</full_title><document_type_detail>product image - not as shown</document_type_detail><document_type>web standard graphic</document_type><dpi_resolution>72</dpi_resolution></image><image><cmg_acronym>cmg518</cmg_acronym><master_object_name>c04537784</master_object_name><content_type>jpg</content_type><image_url_https>https://h10003.www1.hp.com/digmedialib/prodimg/lowres/c04537798.jpg</image_url_https><pixel_height>72</pixel_height><file_name>c04537798.jpg</file_name><orientation>Left facing</orientation><pixel_width>96</pixel_width><action>touch</action><image_url_http>http://h10003.www1.hp.com/digmedialib/prodimg/lowres/c04537798.jpg</image_url_http><background>White</background><full_title>HP OMEN 15-5000 Notebook PC</full_title><document_type_detail>product image - not as shown</document_type_detail><document_type>web standard graphic</document_type><dpi_resolution>72</dpi_resolution></image><image><cmg_acronym>cmg518</cmg_acronym><master_object_name>c04537696</master_object_name><content_type>png</content_type><image_url_https>https://h10003.www1.hp.com/digmedialib/prodimg/lowres/c04537714.png</image_url_https><pixel_height>41</pixel_height><file_name>c04537714.png</file_name><orientation>Center facing</orientation><pixel_width>54</pixel_width><action>touch</action><image_url_http>http://h10003.www1.hp.com/digmedialib/prodimg/lowres/c04537714.png</image_url_http><background>Transparent</background><full_title>HP OMEN 15-5000 Notebook PC</full_title><document_type_detail>product image - not as shown</document_type_detail><document_type>web standard graphic</document_type><dpi_resolution>72</dpi_resolution></image><image><cmg_acronym>cmg518</cmg_acronym><master_object_name>c04537743</master_object_name><content_type>png</content_type><image_url_https>https://h10003.www1.hp.com/digmedialib/prodimg/lowres/c04537743.png</image_url_https><pixel_height>2157</pixel_height><file_name>c04537743.png</file_name><orientation>Right facing</orientation><pixel_width>3120</pixel_width><action>touch</action><image_url_http>http://h10003.www1.hp.com/digmedialib/prodimg/lowres/c04537743.png</image_url_http><background>Transparent</background><full_title>HP OMEN 15-5000 Notebook PC</full_title><document_type_detail>product image - not as shown</document_type_detail><document_type>web standard graphic</document_type><dpi_resolution>300</dpi_resolution></image><image><cmg_acronym>cmg518</cmg_acronym><master_object_name>c04537743</master_object_name><content_type>png</content_type><image_url_https>https://h10003.www1.hp.com/digmedialib/prodimg/lowres/c04537758.png</image_url_https><pixel_height>72</pixel_height><file_name>c04537758.png</file_name><orientation>Right facing</orientation><pixel_width>96</pixel_width><action>touch</action><image_url_http>http://h10003.www1.hp.com/digmedialib/prodimg/lowres/c04537758.png</image_url_http><background>Transparent</background><full_title>HP OMEN 15-5000 Notebook PC</full_title><document_type_detail>product image - not as shown</document_type_detail><document_type>web standard graphic</document_type><dpi_resolution>72</dpi_resolution></image><image><cmg_acronym>cmg518</cmg_acronym><master_object_name>c04537784</master_object_name><content_type>jpg</content_type><image_url_https>https://h10003.www1.hp.com/digmedialib/prodimg/lowres/c04537802.jpg</image_url_https><pixel_height>180</pixel_height><file_name>c04537802.jpg</file_name><orientation>Left facing</orientation><pixel_width>240</pixel_width><action>touch</action><image_url_http>http://h10003.www1.hp.com/digmedialib/prodimg/lowres/c04537802.jpg</image_url_http><background>White</background><full_title>HP OMEN 15-5000 Notebook PC</full_title><document_type_detail>product image - not as shown</document_type_detail><document_type>web standard graphic</document_type><dpi_resolution>72</dpi_resolution></image><image><cmg_acronym>cmg518</cmg_acronym><master_object_name>c04537696</master_object_name><content_type>png</content_type><image_url_https>https://h10003.www1.hp.com/digmedialib/prodimg/lowres/c04537698.png</image_url_https><pixel_height>356</pixel_height><file_name>c04537698.png</file_name><orientation>Center facing</orientation><pixel_width>474</pixel_width><action>touch</action><image_url_http>http://h10003.www1.hp.com/digmedialib/prodimg/lowres/c04537698.png</image_url_http><background>Transparent</background><full_title>HP OMEN 15-5000 Notebook PC</full_title><document_type_detail>product image - not as shown</document_type_detail><document_type>web standard graphic</document_type><dpi_resolution>72</dpi_resolution></image><image><cmg_acronym>cmg518</cmg_acronym><master_object_name>c04537696</master_object_name><content_type>png</content_type><image_url_https>https://h10003.www1.hp.com/digmedialib/prodimg/lowres/c04537711.png</image_url_https><pixel_height>180</pixel_height><file_name>c04537711.png</file_name><orientation>Center facing</orientation><pixel_width>240</pixel_width><action>touch</action><image_url_http>http://h10003.www1.hp.com/digmedialib/prodimg/lowres/c04537711.png</image_url_http><background>Transparent</background><full_title>HP OMEN 15-5000 Notebook PC</full_title><document_type_detail>product image - not as shown</document_type_detail><document_type>web standard graphic</document_type><dpi_resolution>72</dpi_resolution></image><image><cmg_acronym>cmg518</cmg_acronym><master_object_name>c04537743</master_object_name><content_type>png</content_type><image_url_https>https://h10003.www1.hp.com/digmedialib/prodimg/lowres/c04537750.png</image_url_https><pixel_height>185</pixel_height><file_name>c04537750.png</file_name><orientation>Right facing</orientation><pixel_width>247</pixel_width><action>touch</action><image_url_http>http://h10003.www1.hp.com/digmedialib/prodimg/lowres/c04537750.png</image_url_http><background>Transparent</background><full_title>HP OMEN 15-5000 Notebook PC</full_title><document_type_detail>product image - not as shown</document_type_detail><document_type>web standard graphic</document_type><dpi_resolution>72</dpi_resolution></image><image><cmg_acronym>cmg518</cmg_acronym><master_object_name>c04537743</master_object_name><content_type>png</content_type><image_url_https>https://h10003.www1.hp.com/digmedialib/prodimg/lowres/c04537747.png</image_url_https><pixel_height>74</pixel_height><file_name>c04537747.png</file_name><orientation>Right facing</orientation><pixel_width>99</pixel_width><action>touch</action><image_url_http>http://h10003.www1.hp.com/digmedialib/prodimg/lowres/c04537747.png</image_url_http><background>Transparent</background><full_title>HP OMEN 15-5000 Notebook PC</full_title><document_type_detail>product image - not as shown</document_type_detail><document_type>web standard graphic</document_type><dpi_resolution>72</dpi_resolution></image><image><cmg_acronym>cmg518</cmg_acronym><master_object_name>c04537784</master_object_name><content_type>png</content_type><image_url_https>https://h10003.www1.hp.com/digmedialib/prodimg/lowres/c04537785.png</image_url_https><pixel_height>41</pixel_height><file_name>c04537785.png</file_name><orientation>Left facing</orientation><pixel_width>54</pixel_width><action>touch</action><image_url_http>http://h10003.www1.hp.com/digmedialib/prodimg/lowres/c04537785.png</image_url_http><background>Transparent</background><full_title>HP OMEN 15-5000 Notebook PC</full_title><document_type_detail>product image - not as shown</document_type_detail><document_type>web standard graphic</document_type><dpi_resolution>72</dpi_resolution></image><image><cmg_acronym>cmg518</cmg_acronym><master_object_name>c04537784</master_object_name><content_type>png</content_type><image_url_https>https://h10003.www1.hp.com/digmedialib/prodimg/lowres/c04537797.png</image_url_https><pixel_height>430</pixel_height><file_name>c04537797.png</file_name><orientation>Left facing</orientation><pixel_width>573</pixel_width><action>touch</action><image_url_http>http://h10003.www1.hp.com/digmedialib/prodimg/lowres/c04537797.png</image_url_http><background>Transparent</background><full_title>HP OMEN 15-5000 Notebook PC</full_title><document_type_detail>product image - not as shown</document_type_detail><document_type>web standard graphic</document_type><dpi_resolution>72</dpi_resolution></image><image><cmg_acronym>cmg518</cmg_acronym><master_object_name>c04537851</master_object_name><content_type>png</content_type><image_url_https>https://h10003.www1.hp.com/digmedialib/prodimg/lowres/c04537857.png</image_url_https><pixel_height>193</pixel_height><file_name>c04537857.png</file_name><orientation>Left rear facing</orientation><pixel_width>257</pixel_width><action>touch</action><image_url_http>http://h10003.www1.hp.com/digmedialib/prodimg/lowres/c04537857.png</image_url_http><background>Transparent</background><full_title>HP OMEN 15-5000 Notebook PC</full_title><document_type_detail>product image - not as shown</document_type_detail><document_type>web standard graphic</document_type><dpi_resolution>72</dpi_resolution></image><image><cmg_acronym>cmg518</cmg_acronym><master_object_name>c04537851</master_object_name><content_type>png</content_type><image_url_https>https://h10003.www1.hp.com/digmedialib/prodimg/lowres/c04537861.png</image_url_https><pixel_height>180</pixel_height><file_name>c04537861.png</file_name><orientation>Left rear facing</orientation><pixel_width>240</pixel_width><action>touch</action><image_url_http>http://h10003.www1.hp.com/digmedialib/prodimg/lowres/c04537861.png</image_url_http><background>Transparent</background><full_title>HP OMEN 15-5000 Notebook PC</full_title><document_type_detail>product image - not as shown</document_type_detail><document_type>web standard graphic</document_type><dpi_resolution>72</dpi_resolution></image><image><cmg_acronym>cmg518</cmg_acronym><master_object_name>c04537743</master_object_name><content_type>png</content_type><image_url_https>https://h10003.www1.hp.com/digmedialib/prodimg/lowres/c04537755.png</image_url_https><pixel_height>193</pixel_height><file_name>c04537755.png</file_name><orientation>Right facing</orientation><pixel_width>257</pixel_width><action>touch</action><image_url_http>http://h10003.www1.hp.com/digmedialib/prodimg/lowres/c04537755.png</image_url_http><background>Transparent</background><full_title>HP OMEN 15-5000 Notebook PC</full_title><document_type_detail>product image - not as shown</document_type_detail><document_type>web standard graphic</document_type><dpi_resolution>72</dpi_resolution></image><image><cmg_acronym>cmg518</cmg_acronym><master_object_name>c04537743</master_object_name><content_type>jpg</content_type><image_url_https>https://h10003.www1.hp.com/digmedialib/prodimg/lowres/c04537760.jpg</image_url_https><pixel_height>240</pixel_height><file_name>c04537760.jpg</file_name><orientation>Right facing</orientation><pixel_width>320</pixel_width><action>touch</action><image_url_http>http://h10003.www1.hp.com/digmedialib/prodimg/lowres/c04537760.jpg</image_url_http><background>White</background><full_title>HP OMEN 15-5000 Notebook PC</full_title><document_type_detail>product image - not as shown</document_type_detail><document_type>web standard graphic</document_type><dpi_resolution>72</dpi_resolution></image><image><cmg_acronym>cmg518</cmg_acronym><master_object_name>c04537784</master_object_name><content_type>png</content_type><image_url_https>https://h10003.www1.hp.com/digmedialib/prodimg/lowres/c04537793.png</image_url_https><pixel_height>356</pixel_height><file_name>c04537793.png</file_name><orientation>Left facing</orientation><pixel_width>474</pixel_width><action>touch</action><image_url_http>http://h10003.www1.hp.com/digmedialib/prodimg/lowres/c04537793.png</image_url_http><background>Transparent</background><full_title>HP OMEN 15-5000 Notebook PC</full_title><document_type_detail>product image - not as shown</document_type_detail><document_type>web standard graphic</document_type><dpi_resolution>72</dpi_resolution></image><image><cmg_acronym>cmg518</cmg_acronym><master_object_name>c04537784</master_object_name><content_type>png</content_type><image_url_https>https://h10003.www1.hp.com/digmedialib/prodimg/lowres/c04537796.png</image_url_https><pixel_height>240</pixel_height><file_name>c04537796.png</file_name><orientation>Left facing</orientation><pixel_width>320</pixel_width><action>touch</action><image_url_http>http://h10003.www1.hp.com/digmedialib/prodimg/lowres/c04537796.png</image_url_http><background>Transparent</background><full_title>HP OMEN 15-5000 Notebook PC</full_title><document_type_detail>product image - not as shown</document_type_detail><document_type>web standard graphic</document_type><dpi_resolution>72</dpi_resolution></image><image><cmg_acronym>cmg518</cmg_acronym><master_object_name>c04537784</master_object_name><content_type>png</content_type><image_url_https>https://h10003.www1.hp.com/digmedialib/prodimg/lowres/c04537799.png</image_url_https><pixel_height>72</pixel_height><file_name>c04537799.png</file_name><orientation>Left facing</orientation><pixel_width>96</pixel_width><action>touch</action><image_url_http>http://h10003.www1.hp.com/digmedialib/prodimg/lowres/c04537799.png</image_url_http><background>Transparent</background><full_title>HP OMEN 15-5000 Notebook PC</full_title><document_type_detail>product image - not as shown</document_type_detail><document_type>web standard graphic</document_type><dpi_resolution>72</dpi_resolution></image><image><cmg_acronym>cmg518</cmg_acronym><master_object_name>c04537851</master_object_name><content_type>jpg</content_type><image_url_https>https://h10003.www1.hp.com/digmedialib/prodimg/lowres/c04537860.jpg</image_url_https><pixel_height>240</pixel_height><file_name>c04537860.jpg</file_name><orientation>Left rear facing</orientation><pixel_width>320</pixel_width><action>touch</action><image_url_http>http://h10003.www1.hp.com/digmedialib/prodimg/lowres/c04537860.jpg</image_url_http><background>White</background><full_title>HP OMEN 15-5000 Notebook PC</full_title><document_type_detail>product image - not as shown</document_type_detail><document_type>web standard graphic</document_type><dpi_resolution>72</dpi_resolution></image><image><cmg_acronym>cmg518</cmg_acronym><master_object_name>c04537784</master_object_name><content_type>png</content_type><image_url_https>https://h10003.www1.hp.com/digmedialib/prodimg/lowres/c04537801.png</image_url_https><pixel_height>385</pixel_height><file_name>c04537801.png</file_name><orientation>Left facing</orientation><pixel_width>513</pixel_width><action>touch</action><image_url_http>http://h10003.www1.hp.com/digmedialib/prodimg/lowres/c04537801.png</image_url_http><background>Transparent</background><full_title>HP OMEN 15-5000 Notebook PC</full_title><document_type_detail>product image - not as shown</document_type_detail><document_type>web standard graphic</document_type><dpi_resolution>72</dpi_resolution></image><image><cmg_acronym>cmg518</cmg_acronym><master_object_name>c04537851</master_object_name><content_type>png</content_type><image_url_https>https://h10003.www1.hp.com/digmedialib/prodimg/lowres/c04537870.png</image_url_https><pixel_height>185</pixel_height><file_name>c04537870.png</file_name><orientation>Left rear facing</orientation><pixel_width>247</pixel_width><action>touch</action><image_url_http>http://h10003.www1.hp.com/digmedialib/prodimg/lowres/c04537870.png</image_url_http><background>Transparent</background><full_title>HP OMEN 15-5000 Notebook PC</full_title><document_type_detail>product image - not as shown</document_type_detail><document_type>web standard graphic</document_type><dpi_resolution>72</dpi_resolution></image><image><cmg_acronym>cmg518</cmg_acronym><master_object_name>c04537696</master_object_name><content_type>jpg</content_type><image_url_https>https://h10003.www1.hp.com/digmedialib/prodimg/lowres/c04537707.jpg</image_url_https><pixel_height>180</pixel_height><file_name>c04537707.jpg</file_name><orientation>Center facing</orientation><pixel_width>240</pixel_width><action>touch</action><image_url_http>http://h10003.www1.hp.com/digmedialib/prodimg/lowres/c04537707.jpg</image_url_http><background>White</background><full_title>HP OMEN 15-5000 Notebook PC</full_title><document_type_detail>product image - not as shown</document_type_detail><document_type>web standard graphic</document_type><dpi_resolution>72</dpi_resolution></image><image><cmg_acronym>cmg518</cmg_acronym><master_object_name>c04537696</master_object_name><content_type>jpg</content_type><image_url_https>https://h10003.www1.hp.com/digmedialib/prodimg/lowres/c04537708.jpg</image_url_https><pixel_height>41</pixel_height><file_name>c04537708.jpg</file_name><orientation>Center facing</orientation><pixel_width>54</pixel_width><action>touch</action><image_url_http>http://h10003.www1.hp.com/digmedialib/prodimg/lowres/c04537708.jpg</image_url_http><background>White</background><full_title>HP OMEN 15-5000 Notebook PC</full_title><document_type_detail>product image - not as shown</document_type_detail><document_type>web standard graphic</document_type><dpi_resolution>72</dpi_resolution></image><image><cmg_acronym>cmg518</cmg_acronym><master_object_name>c04537743</master_object_name><content_type>jpg</content_type><image_url_https>https://h10003.www1.hp.com/digmedialib/prodimg/lowres/c04537752.jpg</image_url_https><pixel_height>72</pixel_height><file_name>c04537752.jpg</file_name><orientation>Right facing</orientation><pixel_width>96</pixel_width><action>touch</action><image_url_http>http://h10003.www1.hp.com/digmedialib/prodimg/lowres/c04537752.jpg</image_url_http><background>White</background><full_title>HP OMEN 15-5000 Notebook PC</full_title><document_type_detail>product image - not as shown</document_type_detail><document_type>web standard graphic</document_type><dpi_resolution>72</dpi_resolution></image><image><cmg_acronym>cmg518</cmg_acronym><master_object_name>c04537784</master_object_name><content_type>png</content_type><image_url_https>https://h10003.www1.hp.com/digmedialib/prodimg/lowres/c04537786.png</image_url_https><pixel_height>115</pixel_height><file_name>c04537786.png</file_name><orientation>Left facing</orientation><pixel_width>153</pixel_width><action>touch</action><image_url_http>http://h10003.www1.hp.com/digmedialib/prodimg/lowres/c04537786.png</image_url_http><background>Transparent</background><full_title>HP OMEN 15-5000 Notebook PC</full_title><document_type_detail>product image - not as shown</document_type_detail><document_type>web standard graphic</document_type><dpi_resolution>72</dpi_resolution></image><image><cmg_acronym>cmg518</cmg_acronym><master_object_name>c04537743</master_object_name><content_type>jpg</content_type><image_url_https>https://h10003.www1.hp.com/digmedialib/prodimg/lowres/c04537754.jpg</image_url_https><pixel_height>41</pixel_height><file_name>c04537754.jpg</file_name><orientation>Right facing</orientation><pixel_width>54</pixel_width><action>touch</action><image_url_http>http://h10003.www1.hp.com/digmedialib/prodimg/lowres/c04537754.jpg</image_url_http><background>White</background><full_title>HP OMEN 15-5000 Notebook PC</full_title><document_type_detail>product image - not as shown</document_type_detail><document_type>web standard graphic</document_type><dpi_resolution>72</dpi_resolution></image><image><cmg_acronym>cmg518</cmg_acronym><master_object_name>c04537784</master_object_name><content_type>png</content_type><image_url_https>https://h10003.www1.hp.com/digmedialib/prodimg/lowres/c04537784.png</image_url_https><pixel_height>2157</pixel_height><file_name>c04537784.png</file_name><orientation>Left facing</orientation><pixel_width>3120</pixel_width><action>touch</action><image_url_http>http://h10003.www1.hp.com/digmedialib/prodimg/lowres/c04537784.png</image_url_http><background>Transparent</background><full_title>HP OMEN 15-5000 Notebook PC</full_title><document_type_detail>product image - not as shown</document_type_detail><document_type>web standard graphic</document_type><dpi_resolution>300</dpi_resolution></image><image><cmg_acronym>cmg518</cmg_acronym><master_object_name>c04537743</master_object_name><content_type>png</content_type><image_url_https>https://h10003.www1.hp.com/digmedialib/prodimg/lowres/c04537756.png</image_url_https><pixel_height>180</pixel_height><file_name>c04537756.png</file_name><orientation>Right facing</orientation><pixel_width>240</pixel_width><action>touch</action><image_url_http>http://h10003.www1.hp.com/digmedialib/prodimg/lowres/c04537756.png</image_url_http><background>Transparent</background><full_title>HP OMEN 15-5000 Notebook PC</full_title><document_type_detail>product image - not as shown</document_type_detail><document_type>web standard graphic</document_type><dpi_resolution>72</dpi_resolution></image><image><cmg_acronym>cmg518</cmg_acronym><master_object_name>c04537784</master_object_name><content_type>png</content_type><image_url_https>https://h10003.www1.hp.com/digmedialib/prodimg/lowres/c04537789.png</image_url_https><pixel_height>185</pixel_height><file_name>c04537789.png</file_name><orientation>Left facing</orientation><pixel_width>247</pixel_width><action>touch</action><image_url_http>http://h10003.www1.hp.com/digmedialib/prodimg/lowres/c04537789.png</image_url_http><background>Transparent</background><full_title>HP OMEN 15-5000 Notebook PC</full_title><document_type_detail>product image - not as shown</document_type_detail><document_type>web standard graphic</document_type><dpi_resolution>72</dpi_resolution></image><image><cmg_acronym>cmg518</cmg_acronym><master_object_name>c04537696</master_object_name><content_type>png</content_type><image_url_https>https://h10003.www1.hp.com/digmedialib/prodimg/lowres/c04537701.png</image_url_https><pixel_height>385</pixel_height><file_name>c04537701.png</file_name><orientation>Center facing</orientation><pixel_width>513</pixel_width><action>touch</action><image_url_http>http://h10003.www1.hp.com/digmedialib/prodimg/lowres/c04537701.png</image_url_http><background>Transparent</background><full_title>HP OMEN 15-5000 Notebook PC</full_title><document_type_detail>product image - not as shown</document_type_detail><document_type>web standard graphic</document_type><dpi_resolution>72</dpi_resolution></image><image><cmg_acronym>cmg518</cmg_acronym><master_object_name>c04537696</master_object_name><content_type>png</content_type><image_url_https>https://h10003.www1.hp.com/digmedialib/prodimg/lowres/c04537704.png</image_url_https><pixel_height>430</pixel_height><file_name>c04537704.png</file_name><orientation>Center facing</orientation><pixel_width>573</pixel_width><action>touch</action><image_url_http>http://h10003.www1.hp.com/digmedialib/prodimg/lowres/c04537704.png</image_url_http><background>Transparent</background><full_title>HP OMEN 15-5000 Notebook PC</full_title><document_type_detail>product image - not as shown</document_type_detail><document_type>web standard graphic</document_type><dpi_resolution>72</dpi_resolution></image><image><cmg_acronym>cmg518</cmg_acronym><master_object_name>c04537696</master_object_name><content_type>png</content_type><image_url_https>https://h10003.www1.hp.com/digmedialib/prodimg/lowres/c04537696.png</image_url_https><pixel_height>2438</pixel_height><file_name>c04537696.png</file_name><orientation>Center facing</orientation><pixel_width>3161</pixel_width><action>touch</action><image_url_http>http://h10003.www1.hp.com/digmedialib/prodimg/lowres/c04537696.png</image_url_http><background>Transparent</background><full_title>HP OMEN 15-5000 Notebook PC</full_title><document_type_detail>product image - not as shown</document_type_detail><document_type>web standard graphic</document_type><dpi_resolution>300</dpi_resolution></image><image><cmg_acronym>cmg518</cmg_acronym><master_object_name>c04537851</master_object_name><content_type>png</content_type><image_url_https>https://h10003.www1.hp.com/digmedialib/prodimg/lowres/c04537866.png</image_url_https><pixel_height>74</pixel_height><file_name>c04537866.png</file_name><orientation>Left rear facing</orientation><pixel_width>99</pixel_width><action>touch</action><image_url_http>http://h10003.www1.hp.com/digmedialib/prodimg/lowres/c04537866.png</image_url_http><background>Transparent</background><full_title>HP OMEN 15-5000 Notebook PC</full_title><document_type_detail>product image - not as shown</document_type_detail><document_type>web standard graphic</document_type><dpi_resolution>72</dpi_resolution></image><image><cmg_acronym>cmg518</cmg_acronym><master_object_name>c04537851</master_object_name><content_type>png</content_type><image_url_https>https://h10003.www1.hp.com/digmedialib/prodimg/lowres/c04537868.png</image_url_https><pixel_height>385</pixel_height><file_name>c04537868.png</file_name><orientation>Left rear facing</orientation><pixel_width>513</pixel_width><action>touch</action><image_url_http>http://h10003.www1.hp.com/digmedialib/prodimg/lowres/c04537868.png</image_url_http><background>Transparent</background><full_title>HP OMEN 15-5000 Notebook PC</full_title><document_type_detail>product image - not as shown</document_type_detail><document_type>web standard graphic</document_type><dpi_resolution>72</dpi_resolution></image><image><cmg_acronym>cmg518</cmg_acronym><master_object_name>c04537784</master_object_name><content_type>png</content_type><image_url_https>https://h10003.www1.hp.com/digmedialib/prodimg/lowres/c04537800.png</image_url_https><pixel_height>193</pixel_height><file_name>c04537800.png</file_name><orientation>Left facing</orientation><pixel_width>257</pixel_width><action>touch</action><image_url_http>http://h10003.www1.hp.com/digmedialib/prodimg/lowres/c04537800.png</image_url_http><background>Transparent</background><full_title>HP OMEN 15-5000 Notebook PC</full_title><document_type_detail>product image - not as shown</document_type_detail><document_type>web standard graphic</document_type><dpi_resolution>72</dpi_resolution></image><image><cmg_acronym>cmg518</cmg_acronym><master_object_name>c04537851</master_object_name><content_type>png</content_type><image_url_https>https://h10003.www1.hp.com/digmedialib/prodimg/lowres/c04537851.png</image_url_https><pixel_height>2525</pixel_height><file_name>c04537851.png</file_name><orientation>Left rear facing</orientation><pixel_width>3120</pixel_width><action>touch</action><image_url_http>http://h10003.www1.hp.com/digmedialib/prodimg/lowres/c04537851.png</image_url_http><background>Transparent</background><full_title>HP OMEN 15-5000 Notebook PC</full_title><document_type_detail>product image - not as shown</document_type_detail><document_type>web standard graphic</document_type><dpi_resolution>300</dpi_resolution></image><image><cmg_acronym>cmg518</cmg_acronym><master_object_name>c04537784</master_object_name><content_type>png</content_type><image_url_https>https://h10003.www1.hp.com/digmedialib/prodimg/lowres/c04537803.png</image_url_https><pixel_height>180</pixel_height><file_name>c04537803.png</file_name><orientation>Left facing</orientation><pixel_width>240</pixel_width><action>touch</action><image_url_http>http://h10003.www1.hp.com/digmedialib/prodimg/lowres/c04537803.png</image_url_http><background>Transparent</background><full_title>HP OMEN 15-5000 Notebook PC</full_title><document_type_detail>product image - not as shown</document_type_detail><document_type>web standard graphic</document_type><dpi_resolution>72</dpi_resolution></image><image><cmg_acronym>cmg518</cmg_acronym><master_object_name>c04537696</master_object_name><content_type>png</content_type><image_url_https>https://h10003.www1.hp.com/digmedialib/prodimg/lowres/c04537709.png</image_url_https><pixel_height>240</pixel_height><file_name>c04537709.png</file_name><orientation>Center facing</orientation><pixel_width>320</pixel_width><action>touch</action><image_url_http>http://h10003.www1.hp.com/digmedialib/prodimg/lowres/c04537709.png</image_url_http><background>Transparent</background><full_title>HP OMEN 15-5000 Notebook PC</full_title><document_type_detail>product image - not as shown</document_type_detail><document_type>web standard graphic</document_type><dpi_resolution>72</dpi_resolution></image><image><cmg_acronym>cmg518</cmg_acronym><master_object_name>c04537696</master_object_name><content_type>jpg</content_type><image_url_https>https://h10003.www1.hp.com/digmedialib/prodimg/lowres/c04537700.jpg</image_url_https><pixel_height>72</pixel_height><file_name>c04537700.jpg</file_name><orientation>Center facing</orientation><pixel_width>96</pixel_width><action>touch</action><image_url_http>http://h10003.www1.hp.com/digmedialib/prodimg/lowres/c04537700.jpg</image_url_http><background>White</background><full_title>HP OMEN 15-5000 Notebook PC</full_title><document_type_detail>product image - not as shown</document_type_detail><document_type>web standard graphic</document_type><dpi_resolution>72</dpi_resolution></image><image><cmg_acronym>cmg518</cmg_acronym><master_object_name>c04537743</master_object_name><content_type>png</content_type><image_url_https>https://h10003.www1.hp.com/digmedialib/prodimg/lowres/c04537751.png</image_url_https><pixel_height>115</pixel_height><file_name>c04537751.png</file_name><orientation>Right facing</orientation><pixel_width>153</pixel_width><action>touch</action><image_url_http>http://h10003.www1.hp.com/digmedialib/prodimg/lowres/c04537751.png</image_url_http><background>Transparent</background><full_title>HP OMEN 15-5000 Notebook PC</full_title><document_type_detail>product image - not as shown</document_type_detail><document_type>web standard graphic</document_type><dpi_resolution>72</dpi_resolution></image><image><cmg_acronym>cmg518</cmg_acronym><master_object_name>c04537696</master_object_name><content_type>jpg</content_type><image_url_https>https://h10003.www1.hp.com/digmedialib/prodimg/lowres/c04537713.jpg</image_url_https><pixel_height>240</pixel_height><file_name>c04537713.jpg</file_name><orientation>Center facing</orientation><pixel_width>320</pixel_width><action>touch</action><image_url_http>http://h10003.www1.hp.com/digmedialib/prodimg/lowres/c04537713.jpg</image_url_http><background>White</background><full_title>HP OMEN 15-5000 Notebook PC</full_title><document_type_detail>product image - not as shown</document_type_detail><document_type>web standard graphic</document_type><dpi_resolution>72</dpi_resolution></image><image><cmg_acronym>cmg518</cmg_acronym><master_object_name>c04537696</master_object_name><content_type>png</content_type><image_url_https>https://h10003.www1.hp.com/digmedialib/prodimg/lowres/c04537699.png</image_url_https><pixel_height>74</pixel_height><file_name>c04537699.png</file_name><orientation>Center facing</orientation><pixel_width>99</pixel_width><action>touch</action><image_url_http>http://h10003.www1.hp.com/digmedialib/prodimg/lowres/c04537699.png</image_url_http><background>Transparent</background><full_title>HP OMEN 15-5000 Notebook PC</full_title><document_type_detail>product image - not as shown</document_type_detail><document_type>web standard graphic</document_type><dpi_resolution>72</dpi_resolution></image><image><cmg_acronym>cmg518</cmg_acronym><master_object_name>c04537851</master_object_name><content_type>png</content_type><image_url_https>https://h10003.www1.hp.com/digmedialib/prodimg/lowres/c04537869.png</image_url_https><pixel_height>115</pixel_height><file_name>c04537869.png</file_name><orientation>Left rear facing</orientation><pixel_width>153</pixel_width><action>touch</action><image_url_http>http://h10003.www1.hp.com/digmedialib/prodimg/lowres/c04537869.png</image_url_http><background>Transparent</background><full_title>HP OMEN 15-5000 Notebook PC</full_title><document_type_detail>product image - not as shown</document_type_detail><document_type>web standard graphic</document_type><dpi_resolution>72</dpi_resolution></image><image><cmg_acronym>cmg518</cmg_acronym><master_object_name>c04537851</master_object_name><content_type>png</content_type><image_url_https>https://h10003.www1.hp.com/digmedialib/prodimg/lowres/c04537859.png</image_url_https><pixel_height>41</pixel_height><file_name>c04537859.png</file_name><orientation>Left rear facing</orientation><pixel_width>54</pixel_width><action>touch</action><image_url_http>http://h10003.www1.hp.com/digmedialib/prodimg/lowres/c04537859.png</image_url_http><background>Transparent</background><full_title>HP OMEN 15-5000 Notebook PC</full_title><document_type_detail>product image - not as shown</document_type_detail><document_type>web standard graphic</document_type><dpi_resolution>72</dpi_resolution></image><image><cmg_acronym>cmg518</cmg_acronym><master_object_name>c04537743</master_object_name><content_type>png</content_type><image_url_https>https://h10003.www1.hp.com/digmedialib/prodimg/lowres/c04537757.png</image_url_https><pixel_height>135</pixel_height><file_name>c04537757.png</file_name><orientation>Right facing</orientation><pixel_width>180</pixel_width><action>touch</action><image_url_http>http://h10003.www1.hp.com/digmedialib/prodimg/lowres/c04537757.png</image_url_http><background>Transparent</background><full_title>HP OMEN 15-5000 Notebook PC</full_title><document_type_detail>product image - not as shown</document_type_detail><document_type>web standard graphic</document_type><dpi_resolution>72</dpi_resolution></image><image><cmg_acronym>cmg518</cmg_acronym><master_object_name>c04537851</master_object_name><content_type>png</content_type><image_url_https>https://h10003.www1.hp.com/digmedialib/prodimg/lowres/c04537864.png</image_url_https><pixel_height>135</pixel_height><file_name>c04537864.png</file_name><orientation>Left rear facing</orientation><pixel_width>180</pixel_width><action>touch</action><image_url_http>http://h10003.www1.hp.com/digmedialib/prodimg/lowres/c04537864.png</image_url_http><background>Transparent</background><full_title>HP OMEN 15-5000 Notebook PC</full_title><document_type_detail>product image - not as shown</document_type_detail><document_type>web standard graphic</document_type><dpi_resolution>72</dpi_resolution></image></images></item>
